odoo/addons/ssi_risk_analysis_work_log/README.rst
odoo/addons/ssi_risk_analysis_work_log/__init__.py
odoo/addons/ssi_risk_analysis_work_log/__manifest__.py
odoo/addons/ssi_risk_analysis_work_log/models/__init__.py
odoo/addons/ssi_risk_analysis_work_log/models/risk_analysis.py
odoo/addons/ssi_risk_analysis_work_log/models/risk_analysis_worksheet.py
odoo/addons/ssi_risk_analysis_work_log/static/description/icon.png
odoo14_addon_ssi_risk_analysis_work_log-14.0.1.0.0.dist-info/METADATA
odoo14_addon_ssi_risk_analysis_work_log-14.0.1.0.0.dist-info/WHEEL
odoo14_addon_ssi_risk_analysis_work_log-14.0.1.0.0.dist-info/top_level.txt
odoo14_addon_ssi_risk_analysis_work_log-14.0.1.0.0.dist-info/RECORD
